README.md
setup.cfg
setup.py
pizaa/__init__.py
pizaa/pza.py
pizaa.egg-info/PKG-INFO
pizaa.egg-info/SOURCES.txt
pizaa.egg-info/dependency_links.txt
pizaa.egg-info/not-zip-safe
pizaa.egg-info/requires.txt
pizaa.egg-info/top_level.txt