Metadata-Version: 2.1
Name: pizaa
Version: 0.27
Summary: Python image to ascii-art library
Home-page: UNKNOWN
Author: Kollob
Author-email: mrtnb1998@gmail.com
License: UNKNOWN
Platform: UNKNOWN
